sphinx_md/__init__.py
sphinx_md/convert_html.py
sphinx_md-0.0.4.dist-info/LICENSE
sphinx_md-0.0.4.dist-info/METADATA
sphinx_md-0.0.4.dist-info/WHEEL
sphinx_md-0.0.4.dist-info/top_level.txt
sphinx_md-0.0.4.dist-info/RECORD
