Metadata-Version: 2.1
Name: sphinx-md
Version: 0.0.4
Summary: Sphinx extension to use with Recommonmark or MystParser to fix links to rst from md, links to md from rst, and links to embedded files and dirs.
Home-page: https://github.com/intelkevinputnam/sphinx-md
Author: Kevin Putnam
Author-email: kevin.putnam@intel.com
Classifier: Programming Language :: Python :: 3
Classifier: License :: OSI Approved :: MIT License
Classifier: Operating System :: OS Independent
Requires-Python: >=3.6
License-File: LICENSE
Requires-Dist: recommonmark
Requires-Dist: sphinx-markdown-tables
Requires-Dist: bs4
